merkle_tree_lib/__init__.py
merkle_tree_lib/constants.py
merkle_tree_lib/merkle_tree.py
merkle_tree_lib/merkle_tree_utils.py
merkle_tree_lib/validator.py
merkle_tree_lib-0.1.4.dist-info/METADATA
merkle_tree_lib-0.1.4.dist-info/WHEEL
merkle_tree_lib-0.1.4.dist-info/RECORD
