Metadata-Version: 2.1
Name: merkle-tree-lib
Version: 0.1.4
Summary: 
Author: Gabriel Fior
Author-email: gabriel.fior@outlook.com
Requires-Python: >=3.9,<4.0
Classifier: Programming Language :: Python :: 3
Classifier: Programming Language :: Python :: 3.9
Classifier: Programming Language :: Python :: 3.10
Classifier: Programming Language :: Python :: 3.11
Requires-Dist: pysha3 (>=1.0.2,<2.0.0)
